Escher_legacy-1.7.4.data/data/etc/jupyter/nbconfig/notebook.d/escher.json
Escher_legacy-1.7.4.data/data/share/jupyter/nbextensions/escher/escher.min.js
Escher_legacy-1.7.4.data/data/share/jupyter/nbextensions/escher/escher.min.js.map
Escher_legacy-1.7.4.data/data/share/jupyter/nbextensions/escher/extension.js
escher/__init__.py
escher/plots.py
escher/urls.py
escher/util.py
escher/validate.py
escher/version.py
escher/static/escher.min.js
escher/static/escher.min.js.map
escher/static/extension.js
escher/static/package.json
escher/static/jsonschema/1-0-0
escher/templates/standalone.html
Escher_legacy-1.7.4.dist-info/METADATA
Escher_legacy-1.7.4.dist-info/WHEEL
Escher_legacy-1.7.4.dist-info/top_level.txt
Escher_legacy-1.7.4.dist-info/RECORD
