Metadata-Version: 2.1
Name: Escher-legacy
Version: 1.7.4
Summary: Escher-legacy: A Web Application for Building, Sharing, and Embedding Data-Rich Visualizations of Metabolic Pathways
Home-page: https://escher.github.io
Author: Zachary King
License: MIT
Keywords: visualization,pathway map,metabolism,genome-scale-model,web application,D3.js,biojs
Classifier: Development Status :: 5 - Production/Stable
Classifier: License :: OSI Approved :: MIT License
Classifier: Topic :: Scientific/Engineering
Classifier: Topic :: Scientific/Engineering :: Visualization
Classifier: Programming Language :: Python :: 3
Classifier: Programming Language :: Python :: 3.8
Classifier: Programming Language :: Python :: 3.9
Classifier: Programming Language :: Python :: 3.10
Classifier: Operating System :: OS Independent
Requires-Dist: Jinja2 (>=2.7.3)
Requires-Dist: pytest (>=4.0.1)
Requires-Dist: cobra (>=0.5.0)
Requires-Dist: jsonschema (>=3.0.1)
Requires-Dist: ipywidgets (>=7.4.0)
Requires-Dist: pandas (>=0.18)
Provides-Extra: docs
Requires-Dist: sphinx (>=2.1.1) ; extra == 'docs'
Requires-Dist: sphinx-rtd-theme (>=0.4.3) ; extra == 'docs'
Requires-Dist: nbsphinx (>=0.4.2) ; extra == 'docs'
